lib_clds/__init__.py
lib_clo/__init__.py
lib_clo/data/CC_Practical_7.pdf
lib_clo/data/Cloiud_Computing_Practical 6.docx
lib_clo/data/CloudComputing_Practical1.docx
lib_clo/data/Cloud_Computing_Practical2.docx
lib_clo/data/Cloud_Computing_Practical3.docx
lib_clo/data/Cloud_Computing_Practical4.docx
lib_clo/data/Cloud_Computing_Practical5_Updated.docx
lib_clo-0.1.dist-info/METADATA
lib_clo-0.1.dist-info/WHEEL
lib_clo-0.1.dist-info/top_level.txt
lib_clo-0.1.dist-info/RECORD
